panel_sharing/__init__.py
panel_sharing/config.py
panel_sharing/convert.py
panel_sharing/models.py
panel_sharing/py.typed
panel_sharing/sharing.py
panel_sharing/utils.py
panel_sharing/components/__init__.py
panel_sharing/components/build_project.py
panel_sharing/components/gallery.py
panel_sharing/components/js_actions.py
panel_sharing/components/oauth.py
panel_sharing/components/other.py
panel_sharing/components/project_gallery.py
panel_sharing/components/settings_editor.py
panel_sharing/components/share_project.py
panel_sharing/components/source_editor.py
panel_sharing/components/oauth_button/__init__.py
panel_sharing/examples/basic-app/build/app.html
panel_sharing/examples/basic-app/build/app.js
panel_sharing/examples/basic-app/build/config.json
panel_sharing/examples/basic-app/source/app.py
panel_sharing/examples/basic-app/source/readme.md
panel_sharing/examples/basic-app/source/requirements.txt
panel_sharing/examples/basic-app/source/thumbnail.png
panel_sharing/examples/basic-bokeh-app/build/app.html
panel_sharing/examples/basic-bokeh-app/build/app.js
panel_sharing/examples/basic-bokeh-app/build/config.json
panel_sharing/examples/basic-bokeh-app/source/app.py
panel_sharing/examples/basic-bokeh-app/source/readme.md
panel_sharing/examples/basic-bokeh-app/source/requirements.txt
panel_sharing/examples/basic-bokeh-app/source/thumbnail.png
panel_sharing/examples/basic-matplotlib-app/build/app.html
panel_sharing/examples/basic-matplotlib-app/build/app.js
panel_sharing/examples/basic-matplotlib-app/build/config.json
panel_sharing/examples/basic-matplotlib-app/source/app.py
panel_sharing/examples/basic-matplotlib-app/source/readme.md
panel_sharing/examples/basic-matplotlib-app/source/requirements.txt
panel_sharing/examples/basic-matplotlib-app/source/thumbnail.png
panel_sharing/examples/cross-filtering/build/app.html
panel_sharing/examples/cross-filtering/build/app.js
panel_sharing/examples/cross-filtering/build/config.json
panel_sharing-0.32.0.dist-info/METADATA
panel_sharing-0.32.0.dist-info/WHEEL
panel_sharing-0.32.0.dist-info/top_level.txt
panel_sharing-0.32.0.dist-info/RECORD
